norfair_tracker
